WPBackupTool/CommandLine.py
WPBackupTool/__init__.py
WPBackupTool/Engine/DBBackup.py
WPBackupTool/Engine/FTPBackup.py
WPBackupTool/Engine/SFTPBackup.py
WPBackupTool/Engine/__init__.py
WPBackupTool/Library/MailService.py
WPBackupTool/Library/ThreadWithReturnValue.py
WPBackupTool/Library/__init__.py
WPBackupTool/Library/Config/BackupConfig.py
WPBackupTool/Library/Config/DBConfig.py
WPBackupTool/Library/Config/FTPConfig.py
WPBackupTool/Library/Config/MailConfig.py
WPBackupTool/Library/Config/SMPTConfig.py
WPBackupTool/Library/Config/__init__.py
WPBackupTool/Library/Model/DBLog.py
WPBackupTool/Library/Model/FTPLog.py
WPBackupTool/Library/Model/LogItem.py
WPBackupTool/Library/Model/__init__.py
WPBackupTool/Utils/Constants.py
WPBackupTool/Utils/Helper.py
WPBackupTool/Utils/Logger.py
WPBackupTool/Utils/ZipCompression.py
WPBackupTool/Utils/__init__.py
WPBackupTool-8.dist-info/METADATA
WPBackupTool-8.dist-info/WHEEL
WPBackupTool-8.dist-info/entry_points.txt
WPBackupTool-8.dist-info/top_level.txt
WPBackupTool-8.dist-info/RECORD
