Metadata-Version: 2.1
Name: WPBackupTool
Version: 8
Summary: Create Backups of your Wordpress-Site with ease!
Home-page: https://github.com/dersaschahuber/WPBackupTool
Author: Sascha Huber
Author-email: kontakt@sascha-huber.com
License: UNKNOWN
Platform: UNKNOWN
Classifier: Programming Language :: Python :: 3.6
Classifier: License :: OSI Approved :: MIT License
Classifier: Operating System :: OS Independent
Requires-Dist: paramiko
